{
  "id": "globemart-api-env",
  "name": "GlobeMart API Environment",
  "values": [
    {
      "key": "baseUrl",
      "value": "http://localhost:3001",
      "enabled": true
    },
    {
      "key": "accessToken",
      "value": "",
      "enabled": true
    },
    {
      "key": "refreshToken",
      "value": "",
      "enabled": true
    },
    {
      "key": "userId",
      "value": "",
      "enabled": true
    },
    {
      "key": "productId",
      "value": "1",
      "enabled": true
    },
    {
      "key": "categoryId",
      "value": "1",
      "enabled": true
    }
  ]
}